uvm_testbench/example/top.sv
// FIFO to test out system
module top (
    input logic clk,
    input logic reset,
    input logic r_w,
    input logic en,
    input logic [31:0] in,
    output logic [31:0] out,
    output logic [31:0] fifo[8]
);

  logic full;
  logic empty;
  logic [2:0] wptr;
  logic [2:0] rdptr;

  assign full  = (rdptr - 1) == wptr;
  assign empty = rdptr == wptr;

  always @(posedge clk) begin
    if (reset) begin
      rdptr <= 3'd4;
      wptr  <= 3'd4;
    end else begin
      if (en) begin
        if (!r_w & !empty) begin
          rdptr <= rdptr - 3'd1;
          out   <= fifo[rdptr];
        end else if (r_w & !full) begin
          wptr <= wptr + 3'd1;
          fifo[wptr] <= in;
        end
      end
    end
  end
endmodule

uvm_testbench/example/waveform.vcd
$version Generated by VerilatedVcd $end
$timescale 1ps $end

 $scope module TOP $end
  $var wire  1 ' clk $end
  $var wire  1 * en $end
  $var wire 32 - fifo[0] [31:0] $end
  $var wire 32 . fifo[1] [31:0] $end
  $var wire 32 / fifo[2] [31:0] $end
  $var wire 32 0 fifo[3] [31:0] $end
  $var wire 32 1 fifo[4] [31:0] $end
  $var wire 32 2 fifo[5] [31:0] $end
  $var wire 32 3 fifo[6] [31:0] $end
  $var wire 32 4 fifo[7] [31:0] $end
  $var wire 32 + in [31:0] $end
  $var wire 32 , out [31:0] $end
  $var wire  1 ) r_w $end
  $var wire  1 ( reset $end
  $scope module top $end
   $var wire  1 ' clk $end
   $var wire  1 $ empty $end
   $var wire  1 * en $end
   $var wire 32 - fifo[0] [31:0] $end
   $var wire 32 . fifo[1] [31:0] $end
   $var wire 32 / fifo[2] [31:0] $end
   $var wire 32 0 fifo[3] [31:0] $end
   $var wire 32 1 fifo[4] [31:0] $end
   $var wire 32 2 fifo[5] [31:0] $end
   $var wire 32 3 fifo[6] [31:0] $end
   $var wire 32 4 fifo[7] [31:0] $end
   $var wire  1 # full $end
   $var wire 32 + in [31:0] $end
   $var wire 32 , out [31:0] $end
   $var wire  1 ) r_w $end
   $var wire  3 & rdptr [2:0] $end
   $var wire  1 ( reset $end
   $var wire  3 % wptr [2:0] $end
  $upscope $end
 $upscope $end
$enddefinitions $end


#0
0#
1$
b000 %
b000 &
1'
1(
0)
0*
b00000000000000000000000000000000 +
b00000000000000000000000000000000 ,
b00000000000000000000000000000000 -
b00000000000000000000000000000000 .
b00000000000000000000000000000000 /
b00000000000000000000000000000000 0
b00000000000000000000000000000000 1
b00000000000000000000000000000000 2
b00000000000000000000000000000000 3
b00000000000000000000000000000000 4
#1
0'
#2
b100 %
b100 &
1'
#3
0'
#4
1'
#5
0'
#6
1'
#7
0'
#8
1'
#9
0'
#10
1'
0(
1*
b00000000000000000000000001110011 +
#11
0'
#12
1'
1)
0*
b00000000000000000000000011101100 +
#13
0'
#14
1'
b00000000000000000000000010101011 +
#15
0'
#16
1'
1*
b00000000000000000000000001000110 +
#17
0'
#18
0$
b101 %
1'
b00000000000000000000000001000110 1
#19
0'
#20
b110 %
1'
0)
0*
b00000000000000000000000000011011 +
b00000000000000000000000001000110 2
#21
0'
#22
1'
#23
0'
#24
1'
1)
b00000000000000000000000001011010 +
#25
0'
#26
1'
1*
b00000000000000000000000010011111 +
#27
0'
#28
b111 %
1'
0)
0*
b00000000000000000000000000110010 +
b00000000000000000000000010011111 3
#29
0'
#30
1'
1)
1*
b00000000000000000000000001011000 +
#31
0'
#32
b000 %
1'
0)
b00000000000000000000000001011101 +
b00000000000000000000000001011000 4
#33
0'
#34
b011 &
1'
1)
0*
b00000000000000000000000011101001 +
b00000000000000000000000001000110 ,
#35
0'
#36
1'
0)
1*
b00000000000000000000000010110010 +
#37
0'
#38
b010 &
1'
b00000000000000000000000010110100 +
b00000000000000000000000000000000 ,
#39
0'
#40
1#
b001 &
1'
#41
0'
#42
0#
1$
b000 &
1'
0*
b00000000000000000000000001110100 +
#43
0'
#44
1'
1)
1*
b00000000000000000000000011011100 +
#45
0'
#46
0$
b001 %
1'
0)
b00000000000000000000000000111110 +
b00000000000000000000000011011100 -
#47
0'
#48
b111 &
1'
1)
b00000000000000000000000011111100 +
b00000000000000000000000011011100 ,
