uvm_testbench/example/top.sv
// FIFO to test out system
module top (
    input logic clk,
    input logic reset,
    input logic r_w,
    input logic en,
    input logic [31:0] in,
    output logic [31:0] out,
    output logic [31:0] fifo[8]
);

  logic full;
  logic empty;
  logic [2:0] wptr;
  logic [2:0] rdptr;

  assign full  = (rdptr - 1) == wptr;
  assign empty = rdptr == wptr;

  always @(posedge clk) begin
    if (reset) begin
      rdptr <= 3'd4;
      wptr  <= 3'd4;
    end else begin
      if (en) begin
        if (!r_w & !empty) begin
          rdptr <= rdptr - 3'd1;
          out   <= fifo[rdptr];
        end else if (r_w & !full) begin
          wptr <= wptr + 3'd1;
          fifo[wptr] <= in;
          out <= 3'b0;
        end
      end else begin
        out <= 3'b0;
      end
    end
  end
endmodule

uvm_testbench/example/waveform.vcd
$version Generated by VerilatedVcd $end
$timescale 1ps $end

 $scope module TOP $end
  $var wire  1 ' clk $end
  $var wire  1 * en $end
  $var wire 32 - fifo[0] [31:0] $end
  $var wire 32 . fifo[1] [31:0] $end
  $var wire 32 / fifo[2] [31:0] $end
  $var wire 32 0 fifo[3] [31:0] $end
  $var wire 32 1 fifo[4] [31:0] $end
  $var wire 32 2 fifo[5] [31:0] $end
  $var wire 32 3 fifo[6] [31:0] $end
  $var wire 32 4 fifo[7] [31:0] $end
  $var wire 32 + in [31:0] $end
  $var wire 32 , out [31:0] $end
  $var wire  1 ) r_w $end
  $var wire  1 ( reset $end
  $scope module top $end
   $var wire  1 ' clk $end
   $var wire  1 $ empty $end
   $var wire  1 * en $end
   $var wire 32 - fifo[0] [31:0] $end
   $var wire 32 . fifo[1] [31:0] $end
   $var wire 32 / fifo[2] [31:0] $end
   $var wire 32 0 fifo[3] [31:0] $end
   $var wire 32 1 fifo[4] [31:0] $end
   $var wire 32 2 fifo[5] [31:0] $end
   $var wire 32 3 fifo[6] [31:0] $end
   $var wire 32 4 fifo[7] [31:0] $end
   $var wire  1 # full $end
   $var wire 32 + in [31:0] $end
   $var wire 32 , out [31:0] $end
   $var wire  1 ) r_w $end
   $var wire  3 & rdptr [2:0] $end
   $var wire  1 ( reset $end
   $var wire  3 % wptr [2:0] $end
  $upscope $end
 $upscope $end
$enddefinitions $end


#0
0#
1$
b000 %
b000 &
0'
0(
0)
0*
b00000000000000000000000000000000 +
b00000000000000000000000000000000 ,
b00000000000000000000000000000000 -
b00000000000000000000000000000000 .
b00000000000000000000000000000000 /
b00000000000000000000000000000000 0
b00000000000000000000000000000000 1
b00000000000000000000000000000000 2
b00000000000000000000000000000000 3
b00000000000000000000000000000000 4
#1
b100 %
b100 &
1'
1(
#2
0'
#3
1'
#4
0'
#5
1'
#6
0'
#7
1'
#8
0'
#9
1'
#10
0'
#11
1'
0(
b00000000000000000000000010111110 +
#12
0'
#13
1'
1)
b00000000000000000000000010111010 +
#14
0'
#15
1'
0)
b00000000000000000000000010001000 +
#16
0'
#17
1'
1*
b00000000000000000000000010011111 +
#18
0'
#19
1'
#20
0'
#21
1'
1)
0*
b00000000000000000000000000111001 +
#22
0'
#23
1'
0)
b00000000000000000000000000010100 +
#24
0'
#25
1'
#26
0'
#27
1'
#28
0'
#29
1'
#30
0'
#31
1'
b00000000000000000000000000010110 +
#32
0'
#33
1'
b00000000000000000000000011101111 +
#34
0'
#35
1'
1*
b00000000000000000000000000001010 +
#36
0'
#37
1'
0*
b00000000000000000000000010101001 +
#38
0'
#39
1'
1*
b00000000000000000000000011111110 +
#40
0'
#41
1'
0*
b00000000000000000000000000101110 +
#42
0'
#43
1'
1)
1*
b00000000000000000000000001101110 +
#44
0'
#45
0$
b101 %
1'
0*
b00000000000000000000000000001010 +
b00000000000000000000000001101110 1
#46
0'
#47
1'
0)
b00000000000000000000000001111011 +
#48
0'
#49
1'
b00000000000000000000000011010001 +
